pdfdownload
