Metadata-Version: 1.0
Name: django-pdf-download
Version: 0.2.0
Summary: UNKNOWN
Home-page: https://github.com/tax/django-pdf-download
Author: Paul Tax
Author-email: paultax@gmail.com
License: BSD licence, see LICENCE.txt
Platform: UNKNOWN
